{"type": "Feature", "id": 28677619, "geometry": {"type": "Point", "coordinates": [133.012161, -12.32984]}, "properties": {"woe:id": 28677619, "woe:parent_id": 55864492, "woe:name": "Oenpelli Aerodrome", "woe:placetype": 14, "woe:placetype_name": "Airport", "woe:lang": "ENG", "iso:country": "AU", "meta:provider": ["geoplanet:7.3.1", "geoplanet:7.3.2", "geoplanet:7.4.0", "geoplanet:7.4.1", "geoplanet:7.5.1", "geoplanet:7.5.2", "geoplanet:7.6.0", "geoplanet:7.8.1", "geoplanet:7.9.0", "geoplanet:7.10.0", "geoplanet:8.0.0", "woeplanet:8.0.0"], "meta:indexed": "2020-08-20T20:56:50.371678", "woe:alias_ENG_V": ["Oenpelli Airport"], "meta:updated": "2020-10-14T11:51:59.824823", "woe:hierarchy": {"continent": 55949070, "country": 23424748, "town": 0, "planet": 1, "county": 56072970, "suburb": 0, "state": 2344701, "region": 0, "localadmin": 0}, "woe:timezone_id": 28350879, "woe:hash": "qvy9fg2mrzpz", "woe:centroid": [133.012161, -12.32984], "geom:latitude": -12.32984, "geom:longitude": 133.012161, "geom:hash": "qvy9fg2mrzpz", "woe:latitude": -12.32984, "geom:centroid": [133.012161, -12.32984], "woe:longitude": 133.012161, "woe:repo": "woeplanet-airport-au", "geom:area": 0.0, "woe:scale": 19}}