{"type": "Feature", "id": 12510756, "geometry": {"type": "Point", "coordinates": [149.131897, -32.383301]}, "properties": {"woe:id": 12510756, "woe:parent_id": 28589050, "woe:name": "Springhill Airport", "woe:placetype": 14, "woe:placetype_name": "Airport", "woe:lang": "ENG", "iso:country": "AU", "meta:provider": ["geoplanet:7.3.1", "geoplanet:7.3.2", "geoplanet:7.4.0", "geoplanet:7.4.1", "geoplanet:7.5.1", "geoplanet:7.5.2", "geoplanet:7.6.0", "geoplanet:7.8.1", "geoplanet:7.9.0", "geoplanet:7.10.0", "geoplanet:8.0.0", "woeplanet:8.0.0"], "meta:indexed": "2020-08-20T20:56:50.027090", "woe:alias_ENG_V": ["OAG Airport", "OAG"], "meta:updated": "2020-10-14T11:52:00.147930", "woe:hierarchy": {"continent": 55949070, "country": 23424748, "town": 0, "planet": 1, "county": 55863771, "suburb": 0, "state": 2344700, "region": 0, "localadmin": 0}, "woe:timezone_id": 28350885, "woe:hash": "r64pc8f9954j", "woe:centroid": [149.131897, -32.383301], "geom:latitude": -32.383301, "geom:longitude": 149.131897, "geom:hash": "r64pc8f9954j", "woe:latitude": -32.383301, "geom:centroid": [149.131897, -32.383301], "woe:longitude": 149.131897, "woe:repo": "woeplanet-airport-au", "geom:area": 0.0, "woe:scale": 19}}