{"type": "Feature", "id": 12510794, "properties": {"woe:id": 12510794, "woe:parent_id": 1105949, "woe:name": "Thargomindah Aerodrome", "woe:placetype": 14, "woe:placetype_name": "Airport", "woe:lang": "ENG", "iso:country": "AU", "meta:provider": ["geoplanet:7.3.1", "geoplanet:7.3.2", "geoplanet:7.4.0", "geoplanet:7.4.1", "geoplanet:7.5.1", "geoplanet:7.5.2", "geoplanet:7.6.0", "geoplanet:7.8.1", "geoplanet:7.9.0", "geoplanet:7.10.0", "geoplanet:8.0.0", "woeplanet:8.0.0"], "meta:indexed": "2020-08-20T20:56:50.041255", "woe:alias_ENG_V": ["Thargomindah Airport"], "meta:updated": "2020-08-22T02:29:09.455294", "woe:hierarchy": {"continent": 55949070, "country": 23424748, "town": 0, "planet": 1, "county": 55863938, "suburb": 0, "state": 2344702, "region": 0, "localadmin": 0}, "woe:timezone_id": 28350878, "woe:hash": "r5n2b9c5cqvn", "woe:centroid": [143.812469, -27.98287], "geom:latitude": -27.98287, "geom:longitude": 143.812469, "geom:hash": "r5n2b9c5cqvn", "woe:latitude": -27.98287, "geom:centroid": [143.812469, -27.98287], "woe:longitude": 143.812469, "woe:repo": "woeplanet-airport-au"}, "geometry": {"coordinates": [143.812469, -27.98287], "type": "Point"}}