{"type": "Feature", "id": 12523123, "properties": {"woe:id": 12523123, "woe:parent_id": 28585427, "woe:name": "Hinchinbrooke Island Airport", "woe:placetype": 14, "woe:placetype_name": "Airport", "woe:lang": "ENG", "iso:country": "AU", "meta:provider": ["geoplanet:7.3.1", "geoplanet:7.3.2", "geoplanet:7.4.0", "geoplanet:7.4.1", "geoplanet:7.5.1", "geoplanet:7.5.2", "geoplanet:7.6.0", "geoplanet:7.8.1", "geoplanet:7.9.0", "geoplanet:7.10.0", "geoplanet:8.0.0", "woeplanet:8.0.0"], "meta:indexed": "2020-08-20T20:56:50.048956", "woe:alias_ENG_V": ["HNK Airport", "HNK", "Hinchinbrooke Island"], "meta:updated": "2020-08-22T02:29:09.459015", "woe:hierarchy": {"continent": 55949070, "country": 23424748, "town": 0, "planet": 1, "county": 0, "suburb": 0, "state": 2344702, "region": 0, "localadmin": 0}, "woe:timezone_id": 28350878, "woe:hash": "rk8p2v2m2e0g", "woe:centroid": [146.283325, -18.383329], "geom:latitude": -18.383329, "geom:longitude": 146.283325, "geom:hash": "rk8p2v2m2e0g", "woe:latitude": -18.383329, "geom:centroid": [146.283325, -18.383329], "woe:longitude": 146.283325, "woe:repo": "woeplanet-airport-au"}, "geometry": {"coordinates": [146.283325, -18.383329], "type": "Point"}}