{"type": "Feature", "id": 28743651, "geometry": {"type": "Point", "coordinates": [130.421936, -11.4025]}, "properties": {"woe:id": 28743651, "woe:parent_id": 1105182, "woe:name": "Garden Point Airport", "woe:placetype": 14, "woe:placetype_name": "Airport", "woe:lang": "ENG", "iso:country": "AU", "meta:provider": ["geoplanet:7.3.1", "geoplanet:7.3.2", "geoplanet:7.4.0", "geoplanet:7.4.1", "geoplanet:7.5.1", "geoplanet:7.5.2", "geoplanet:7.6.0", "geoplanet:7.8.1", "geoplanet:7.9.0", "geoplanet:7.10.0", "geoplanet:8.0.0", "woeplanet:8.0.0"], "meta:indexed": "2020-08-20T20:56:50.249449", "woe:alias_ENG_V": ["Garden Point"], "meta:updated": "2020-10-14T11:51:59.969998", "woe:hierarchy": {"continent": 55949070, "country": 23424748, "town": 0, "planet": 1, "county": 56072962, "suburb": 0, "state": 2344701, "region": 0, "localadmin": 0}, "woe:timezone_id": 28350879, "woe:hash": "qvuxpu4re7un", "woe:centroid": [130.421936, -11.4025], "geom:latitude": -11.4025, "geom:longitude": 130.421936, "geom:hash": "qvuxpu4re7un", "woe:latitude": -11.4025, "geom:centroid": [130.421936, -11.4025], "woe:longitude": 130.421936, "woe:repo": "woeplanet-airport-au", "geom:area": 0.0, "woe:scale": 19}}