{"type": "Feature", "id": 12523230, "geometry": {"type": "Point", "coordinates": [145.292297, -42.152191]}, "properties": {"woe:id": 12523230, "woe:parent_id": 1105710, "woe:name": "Strahan Aerodome", "woe:placetype": 14, "woe:placetype_name": "Airport", "woe:lang": "ENG", "iso:country": "AU", "meta:provider": ["geoplanet:7.3.1", "geoplanet:7.3.2", "geoplanet:7.4.0", "geoplanet:7.4.1", "geoplanet:7.5.1", "geoplanet:7.5.2", "geoplanet:7.6.0", "geoplanet:7.8.1", "geoplanet:7.9.0", "geoplanet:7.10.0", "geoplanet:8.0.0", "woeplanet:8.0.0"], "meta:indexed": "2020-08-20T20:56:50.053424", "woe:alias_ENG_V": ["SRN Airport", "SRN", "Strahan Airport"], "meta:updated": "2020-10-14T11:51:59.997284", "woe:hierarchy": {"continent": 55949070, "country": 23424748, "town": 0, "planet": 1, "county": 55864277, "suburb": 0, "state": 2344704, "region": 0, "localadmin": 0}, "woe:timezone_id": 28350880, "woe:hash": "r0x24nqteyhf", "woe:centroid": [145.292297, -42.152191], "geom:latitude": -42.152191, "geom:longitude": 145.292297, "geom:hash": "r0x24nqteyhf", "woe:latitude": -42.152191, "geom:centroid": [145.292297, -42.152191], "woe:longitude": 145.292297, "woe:repo": "woeplanet-airport-au", "geom:area": 0.0, "woe:scale": 19}}