{"type": "Feature", "id": 12510779, "properties": {"woe:id": 12510779, "woe:parent_id": 28585650, "woe:name": "Shepparton Airport", "woe:placetype": 14, "woe:placetype_name": "Airport", "woe:lang": "ENG", "iso:country": "AU", "meta:provider": ["geoplanet:7.3.1", "geoplanet:7.3.2", "geoplanet:7.4.0", "geoplanet:7.4.1", "geoplanet:7.5.1", "geoplanet:7.5.2", "geoplanet:7.6.0", "geoplanet:7.8.1", "geoplanet:7.9.0", "geoplanet:7.10.0", "geoplanet:8.0.0", "woeplanet:8.0.0"], "meta:indexed": "2020-08-20T20:56:50.035964", "meta:updated": "2020-08-22T02:29:09.452554", "woe:hierarchy": {"continent": 55949070, "country": 23424748, "town": 0, "planet": 1, "county": 55863998, "suburb": 0, "state": 2344705, "region": 0, "localadmin": 0}, "woe:timezone_id": 28350883, "woe:hash": "r1x2u2tvk7qh", "woe:centroid": [145.390167, -36.426998], "geom:latitude": -36.426998, "geom:longitude": 145.390167, "geom:hash": "r1x2u2tvk7qh", "woe:latitude": -36.426998, "geom:centroid": [145.390167, -36.426998], "woe:longitude": 145.390167, "woe:repo": "woeplanet-airport-au"}, "geometry": {"coordinates": [145.390167, -36.426998], "type": "Point"}}