{"type": "Feature", "id": 28677775, "properties": {"woe:id": 28677775, "woe:parent_id": 2344706, "woe:name": "Troughton Island Aerodrome", "woe:placetype": 14, "woe:placetype_name": "Airport", "woe:lang": "ENG", "iso:country": "AU", "meta:provider": ["geoplanet:7.3.1", "geoplanet:7.3.2", "geoplanet:7.4.0", "geoplanet:7.4.1", "geoplanet:7.5.1", "geoplanet:7.5.2", "geoplanet:7.6.0", "geoplanet:7.8.1", "geoplanet:7.9.0", "geoplanet:7.10.0", "geoplanet:8.0.0", "woeplanet:8.0.0"], "meta:indexed": "2020-08-20T20:56:50.232766", "meta:updated": "2020-08-22T02:29:09.549181", "woe:hierarchy": {"continent": 55949070, "country": 23424748, "town": 0, "planet": 1, "county": 0, "suburb": 0, "state": 2344706, "region": 0, "localadmin": 0}, "woe:hash": "qv99y8ex1hd6", "woe:centroid": [126.149872, -13.75091], "geom:latitude": -13.75091, "geom:longitude": 126.149872, "geom:hash": "qv99y8ex1hd6", "woe:latitude": -13.75091, "geom:centroid": [126.149872, -13.75091], "woe:longitude": 126.149872, "woe:repo": "woeplanet-airport-au"}, "geometry": {"coordinates": [126.149872, -13.75091], "type": "Point"}}