{"type": "Feature", "id": 56043501, "geometry": {"type": "Point", "coordinates": [115.39846, -33.68594]}, "properties": {"woe:id": 56043501, "woe:parent_id": 28588184, "woe:name": "Busselton Airport", "woe:placetype": 14, "woe:placetype_name": "Airport", "woe:lang": "ENG", "iso:country": "AU", "meta:provider": ["geoplanet:7.3.1", "geoplanet:7.3.2", "geoplanet:7.4.0", "geoplanet:7.4.1", "geoplanet:7.5.1", "geoplanet:7.5.2", "geoplanet:7.6.0", "geoplanet:7.8.1", "geoplanet:7.9.0", "geoplanet:7.10.0", "geoplanet:8.0.0", "woeplanet:8.0.0"], "meta:indexed": "2020-08-20T20:56:50.381601", "meta:updated": "2020-10-14T11:51:59.983463", "woe:hierarchy": {"continent": 55949070, "country": 23424748, "town": 0, "planet": 1, "county": 55864423, "suburb": 0, "state": 2344706, "region": 0, "localadmin": 0}, "woe:timezone_id": 28350884, "woe:hash": "qd403gwt5j8k", "woe:centroid": [115.39846, -33.68594], "geom:latitude": -33.68594, "geom:longitude": 115.39846, "geom:hash": "qd403gwt5j8k", "woe:latitude": -33.68594, "geom:centroid": [115.39846, -33.68594], "woe:longitude": 115.39846, "woe:repo": "woeplanet-airport-au", "geom:area": 0.0, "woe:scale": 19}}