{"type": "Feature", "id": 12510709, "geometry": {"type": "Point", "coordinates": [139.878296, -36.821701]}, "properties": {"woe:id": 12510709, "woe:parent_id": 1096649, "woe:name": "Kingston Southeast Airport", "woe:placetype": 14, "woe:placetype_name": "Airport", "woe:lang": "ENG", "iso:country": "AU", "meta:provider": ["geoplanet:7.3.1", "geoplanet:7.3.2", "geoplanet:7.4.0", "geoplanet:7.4.1", "geoplanet:7.5.1", "geoplanet:7.5.2", "geoplanet:7.6.0", "geoplanet:7.8.1", "geoplanet:7.9.0", "geoplanet:7.10.0", "geoplanet:8.0.0", "woeplanet:8.0.0"], "meta:indexed": "2020-08-20T20:56:50.011796", "meta:updated": "2020-10-14T11:52:00.107212", "woe:hierarchy": {"continent": 55949070, "country": 23424748, "town": 0, "planet": 1, "county": 55864233, "suburb": 0, "state": 2344703, "region": 0, "localadmin": 0}, "woe:timezone_id": 28350877, "woe:hash": "r17qx0b6093j", "woe:centroid": [139.878296, -36.821701], "geom:latitude": -36.821701, "geom:longitude": 139.878296, "geom:hash": "r17qx0b6093j", "woe:latitude": -36.821701, "geom:centroid": [139.878296, -36.821701], "woe:longitude": 139.878296, "woe:repo": "woeplanet-airport-au", "geom:area": 0.0, "woe:scale": 19}}