{"type": "Feature", "id": 12510616, "geometry": {"type": "Point", "coordinates": [146.814087, -29.972071]}, "properties": {"woe:id": 12510616, "woe:parent_id": 1100637, "woe:name": "Brewarrina Aerodrome", "woe:placetype": 14, "woe:placetype_name": "Airport", "woe:lang": "ENG", "iso:country": "AU", "meta:provider": ["geoplanet:7.3.1", "geoplanet:7.3.2", "geoplanet:7.4.0", "geoplanet:7.4.1", "geoplanet:7.5.1", "geoplanet:7.5.2", "geoplanet:7.6.0", "geoplanet:7.8.1", "geoplanet:7.9.0", "geoplanet:7.10.0", "geoplanet:8.0.0", "woeplanet:8.0.0"], "meta:indexed": "2020-08-20T20:56:50.287005", "woe:alias_ENG_V": ["Brewarrina Airport"], "meta:updated": "2020-10-14T11:52:00.067055", "woe:hierarchy": {"continent": 55949070, "country": 23424748, "town": 0, "planet": 1, "county": 55863851, "suburb": 0, "state": 2344700, "region": 0, "localadmin": 0}, "woe:timezone_id": 28350885, "woe:hash": "r68mkzfb01jb", "woe:centroid": [146.814087, -29.972071], "geom:latitude": -29.972071, "geom:longitude": 146.814087, "geom:hash": "r68mkzfb01jb", "woe:latitude": -29.972071, "geom:centroid": [146.814087, -29.972071], "woe:longitude": 146.814087, "woe:repo": "woeplanet-airport-au", "geom:area": 0.0, "woe:scale": 19}}