{"type": "Feature", "id": 28677742, "properties": {"woe:id": 28677742, "woe:parent_id": 1105358, "woe:name": "Boolgeeda Aerodrome", "woe:placetype": 14, "woe:placetype_name": "Airport", "woe:lang": "ENG", "iso:country": "AU", "meta:provider": ["geoplanet:7.3.1", "geoplanet:7.3.2", "geoplanet:7.4.0", "geoplanet:7.4.1", "geoplanet:7.5.1", "geoplanet:7.5.2", "geoplanet:7.6.0", "geoplanet:7.8.1", "geoplanet:7.9.0", "geoplanet:7.10.0", "geoplanet:8.0.0", "woeplanet:8.0.0"], "meta:indexed": "2020-08-20T20:56:50.208275", "meta:updated": "2020-08-22T02:29:09.537795", "woe:hierarchy": {"continent": 55949070, "country": 23424748, "town": 0, "planet": 1, "county": 55864374, "suburb": 0, "state": 2344706, "region": 0, "localadmin": 0}, "woe:timezone_id": 28350884, "woe:hash": "qegru8yuur22", "woe:centroid": [117.277519, -22.538971], "geom:latitude": -22.538971, "geom:longitude": 117.277519, "geom:hash": "qegru8yuur22", "woe:latitude": -22.538971, "geom:centroid": [117.277519, -22.538971], "woe:longitude": 117.277519, "woe:repo": "woeplanet-airport-au"}, "geometry": {"coordinates": [117.277519, -22.538971], "type": "Point"}}