{"type": "Feature", "id": 28677756, "properties": {"woe:id": 28677756, "woe:parent_id": 1104838, "woe:name": "Turner Aerodrome", "woe:placetype": 14, "woe:placetype_name": "Airport", "woe:lang": "ENG", "iso:country": "AU", "meta:provider": ["geoplanet:7.3.1", "geoplanet:7.3.2", "geoplanet:7.4.0", "geoplanet:7.4.1", "geoplanet:7.5.1", "geoplanet:7.5.2", "geoplanet:7.6.0", "geoplanet:7.8.1", "geoplanet:7.9.0", "geoplanet:7.10.0", "geoplanet:8.0.0", "woeplanet:8.0.0"], "meta:indexed": "2020-08-20T20:56:50.219141", "meta:updated": "2020-08-22T02:29:09.543673", "woe:hierarchy": {"continent": 55949070, "country": 23424748, "town": 0, "planet": 1, "county": 55864073, "suburb": 0, "state": 2344706, "region": 0, "localadmin": 0}, "woe:timezone_id": 28350884, "woe:hash": "qug68smfne69", "woe:centroid": [128.350464, -17.81809], "geom:latitude": -17.81809, "geom:longitude": 128.350464, "geom:hash": "qug68smfne69", "woe:latitude": -17.81809, "geom:centroid": [128.350464, -17.81809], "woe:longitude": 128.350464, "woe:repo": "woeplanet-airport-au"}, "geometry": {"coordinates": [128.350464, -17.81809], "type": "Point"}}