{"type": "Feature", "id": 28677626, "geometry": {"type": "Point", "coordinates": [143.711456, -18.851601]}, "properties": {"woe:id": 28677626, "woe:parent_id": 1102087, "woe:name": "Robinhood Aerodrome", "woe:placetype": 14, "woe:placetype_name": "Airport", "woe:lang": "ENG", "iso:country": "AU", "meta:provider": ["geoplanet:7.3.1", "geoplanet:7.3.2", "geoplanet:7.4.0", "geoplanet:7.4.1", "geoplanet:7.5.1", "geoplanet:7.5.2", "geoplanet:7.6.0", "geoplanet:7.8.1", "geoplanet:7.9.0", "geoplanet:7.10.0", "geoplanet:8.0.0", "woeplanet:8.0.0"], "meta:indexed": "2020-08-20T20:56:50.119011", "meta:updated": "2020-10-14T11:51:59.870725", "woe:hierarchy": {"continent": 55949070, "country": 23424748, "town": 0, "planet": 1, "county": 55863919, "suburb": 0, "state": 2344702, "region": 0, "localadmin": 0}, "woe:timezone_id": 28350878, "woe:hash": "rhwhy0pmrwu7", "woe:centroid": [143.711456, -18.851601], "geom:latitude": -18.851601, "geom:longitude": 143.711456, "geom:hash": "rhwhy0pmrwu7", "woe:latitude": -18.851601, "geom:centroid": [143.711456, -18.851601], "woe:longitude": 143.711456, "woe:repo": "woeplanet-airport-au", "geom:area": 0.0, "woe:scale": 19}}