{"type": "Feature", "id": 12510725, "properties": {"woe:id": 12510725, "woe:parent_id": 1098414, "woe:name": "Maitland Airport", "woe:placetype": 14, "woe:placetype_name": "Airport", "woe:lang": "ENG", "iso:country": "AU", "meta:provider": ["geoplanet:7.3.1", "geoplanet:7.3.2", "geoplanet:7.4.0", "geoplanet:7.4.1", "geoplanet:7.5.1", "geoplanet:7.5.2", "geoplanet:7.6.0", "geoplanet:7.8.1", "geoplanet:7.9.0", "geoplanet:7.10.0", "geoplanet:8.0.0", "woeplanet:8.0.0"], "meta:indexed": "2020-08-20T20:56:50.324509", "woe:alias_ENG_V": ["Russell Field", "MTL Airport", "MTL"], "meta:updated": "2020-08-22T02:29:09.589576", "woe:hierarchy": {"continent": 55949070, "country": 23424748, "town": 0, "planet": 1, "county": 55863803, "suburb": 0, "state": 2344700, "region": 0, "localadmin": 0}, "woe:timezone_id": 28350885, "woe:hash": "r65tznpqw4rm", "woe:centroid": [151.489716, -32.70517], "geom:latitude": -32.70517, "geom:longitude": 151.489716, "geom:hash": "r65tznpqw4rm", "woe:latitude": -32.70517, "geom:centroid": [151.489716, -32.70517], "woe:longitude": 151.489716, "woe:repo": "woeplanet-airport-au"}, "geometry": {"coordinates": [151.489716, -32.70517], "type": "Point"}}