{"type": "Feature", "id": 12510693, "properties": {"woe:id": 12510693, "woe:parent_id": 1101710, "woe:name": "Horsham Airport", "woe:placetype": 14, "woe:placetype_name": "Airport", "woe:lang": "ENG", "iso:country": "AU", "meta:provider": ["geoplanet:7.3.1", "geoplanet:7.3.2", "geoplanet:7.4.0", "geoplanet:7.4.1", "geoplanet:7.5.1", "geoplanet:7.5.2", "geoplanet:7.6.0", "geoplanet:7.8.1", "geoplanet:7.9.0", "geoplanet:7.10.0", "geoplanet:8.0.0", "woeplanet:8.0.0"], "meta:indexed": "2020-08-20T20:56:50.003108", "meta:updated": "2020-08-22T02:29:09.437767", "woe:hierarchy": {"continent": 55949070, "country": 23424748, "town": 0, "planet": 1, "county": 55863995, "suburb": 0, "state": 2344705, "region": 0, "localadmin": 0}, "woe:timezone_id": 28350883, "woe:hash": "r1mp7hhkhrnn", "woe:centroid": [142.169113, -36.671638], "geom:latitude": -36.671638, "geom:longitude": 142.169113, "geom:hash": "r1mp7hhkhrnn", "woe:latitude": -36.671638, "geom:centroid": [142.169113, -36.671638], "woe:longitude": 142.169113, "woe:repo": "woeplanet-airport-au"}, "geometry": {"coordinates": [142.169113, -36.671638], "type": "Point"}}