{"type": "Feature", "id": 12510625, "geometry": {"type": "Point", "coordinates": [149.190491, -35.307339]}, "properties": {"woe:id": 12510625, "woe:parent_id": 55863865, "woe:name": "Canberra International Airport", "woe:placetype": 14, "woe:placetype_name": "Airport", "woe:lang": "ENG", "iso:country": "AU", "meta:provider": ["geoplanet:7.3.1", "geoplanet:7.3.2", "geoplanet:7.4.0", "geoplanet:7.4.1", "geoplanet:7.5.1", "geoplanet:7.5.2", "geoplanet:7.6.0", "geoplanet:7.8.1", "geoplanet:7.9.0", "geoplanet:7.10.0", "geoplanet:8.0.0", "woeplanet:8.0.0"], "meta:indexed": "2020-08-20T20:56:50.292398", "woe:alias_ENG_V": ["CBR Airport", "CBR", "Canberra Airport"], "meta:updated": "2020-10-14T11:52:00.022570", "woe:hierarchy": {"continent": 55949070, "country": 23424748, "town": 0, "planet": 1, "county": 55863865, "suburb": 0, "state": 2344699, "region": 0, "localadmin": 0}, "woe:timezone_id": 28350885, "woe:hash": "r3dp4umpy6vp", "woe:centroid": [149.190491, -35.307339], "geom:latitude": -35.307339, "geom:longitude": 149.190491, "geom:hash": "r3dp4umpy6vp", "woe:latitude": -35.307339, "geom:centroid": [149.190491, -35.307339], "woe:longitude": 149.190491, "woe:repo": "woeplanet-airport-au", "geom:area": 0.0, "woe:scale": 19}}