{"type": "Feature", "id": 28677637, "geometry": {"type": "Point", "coordinates": [141.447357, -16.280609]}, "properties": {"woe:id": 28677637, "woe:parent_id": 28588175, "woe:name": "Inkerman Aerodrome", "woe:placetype": 14, "woe:placetype_name": "Airport", "woe:lang": "ENG", "iso:country": "AU", "meta:provider": ["geoplanet:7.3.1", "geoplanet:7.3.2", "geoplanet:7.4.0", "geoplanet:7.4.1", "geoplanet:7.5.1", "geoplanet:7.5.2", "geoplanet:7.6.0", "geoplanet:7.8.1", "geoplanet:7.9.0", "geoplanet:7.10.0", "geoplanet:8.0.0", "woeplanet:8.0.0"], "meta:indexed": "2020-08-20T20:56:50.126690", "meta:updated": "2020-10-14T11:51:59.859335", "woe:hierarchy": {"continent": 55949070, "country": 23424748, "town": 0, "planet": 1, "county": 55864340, "suburb": 0, "state": 2344702, "region": 0, "localadmin": 0}, "woe:timezone_id": 28350878, "woe:hash": "rjhe6snyd69b", "woe:centroid": [141.447357, -16.280609], "geom:latitude": -16.280609, "geom:longitude": 141.447357, "geom:hash": "rjhe6snyd69b", "woe:latitude": -16.280609, "geom:centroid": [141.447357, -16.280609], "woe:longitude": 141.447357, "woe:repo": "woeplanet-airport-au", "geom:area": 0.0, "woe:scale": 19}}