{"type": "Feature", "id": 12510799, "properties": {"woe:id": 12510799, "woe:parent_id": 28588034, "woe:name": "Toowoomba Airport", "woe:placetype": 14, "woe:placetype_name": "Airport", "woe:lang": "ENG", "iso:country": "AU", "meta:provider": ["geoplanet:7.3.1", "geoplanet:7.3.2", "geoplanet:7.4.0", "geoplanet:7.4.1", "geoplanet:7.5.1", "geoplanet:7.5.2", "geoplanet:7.6.0", "geoplanet:7.8.1", "geoplanet:7.9.0", "geoplanet:7.10.0", "geoplanet:8.0.0", "woeplanet:8.0.0"], "meta:indexed": "2020-08-20T20:56:50.352603", "woe:alias_ENG_V": ["TWB Airport", "TWB"], "meta:updated": "2020-08-22T02:29:09.602822", "woe:hierarchy": {"continent": 55949070, "country": 23424748, "town": 0, "planet": 1, "county": 56072999, "suburb": 0, "state": 2344702, "region": 0, "localadmin": 0}, "woe:timezone_id": 28350878, "woe:hash": "r7h52ccctjst", "woe:centroid": [151.910583, -27.54381], "geom:latitude": -27.54381, "geom:longitude": 151.910583, "geom:hash": "r7h52ccctjst", "woe:latitude": -27.54381, "geom:centroid": [151.910583, -27.54381], "woe:longitude": 151.910583, "woe:repo": "woeplanet-airport-au"}, "geometry": {"coordinates": [151.910583, -27.54381], "type": "Point"}}