{"type": "Feature", "id": 12523457, "properties": {"woe:id": 12523457, "woe:parent_id": 55864372, "woe:name": "Leopold Downs Airport", "woe:placetype": 14, "woe:placetype_name": "Airport", "woe:lang": "ENG", "iso:country": "AU", "meta:provider": ["geoplanet:7.3.1", "geoplanet:7.3.2", "geoplanet:7.4.0", "geoplanet:7.4.1", "geoplanet:7.5.1", "geoplanet:7.5.2", "geoplanet:7.6.0", "geoplanet:7.8.1", "geoplanet:7.9.0", "geoplanet:7.10.0", "geoplanet:8.0.0", "woeplanet:8.0.0"], "meta:indexed": "2020-08-20T20:56:50.066062", "meta:updated": "2020-08-22T02:29:09.466468", "woe:hierarchy": {"continent": 55949070, "country": 23424748, "town": 0, "planet": 1, "county": 55864372, "suburb": 0, "state": 2344706, "region": 0, "localadmin": 0}, "woe:timezone_id": 28350884, "woe:hash": "quc4nxq35txt", "woe:centroid": [125.450638, -17.88966], "geom:latitude": -17.88966, "geom:longitude": 125.450638, "geom:hash": "quc4nxq35txt", "woe:latitude": -17.88966, "geom:centroid": [125.450638, -17.88966], "woe:longitude": 125.450638, "woe:repo": "woeplanet-airport-au"}, "geometry": {"coordinates": [125.450638, -17.88966], "type": "Point"}}