{"type": "Feature", "id": 12510667, "geometry": {"type": "Point", "coordinates": [153.416702, -29.1028]}, "properties": {"woe:id": 12510667, "woe:parent_id": 1101996, "woe:name": "Evans Head Airport", "woe:placetype": 14, "woe:placetype_name": "Airport", "woe:lang": "ENG", "iso:country": "AU", "meta:provider": ["geoplanet:7.3.1", "geoplanet:7.3.2", "geoplanet:7.4.0", "geoplanet:7.4.1", "geoplanet:7.5.1", "geoplanet:7.5.2", "geoplanet:7.6.0", "geoplanet:7.8.1", "geoplanet:7.9.0", "geoplanet:7.10.0", "geoplanet:8.0.0", "woeplanet:8.0.0"], "meta:indexed": "2020-08-20T20:56:49.991832", "meta:updated": "2020-10-14T11:52:00.053778", "woe:hierarchy": {"continent": 55949070, "country": 23424748, "town": 0, "planet": 1, "county": 55864299, "suburb": 0, "state": 2344700, "region": 0, "localadmin": 0}, "woe:timezone_id": 28350885, "woe:hash": "r6v47jfxukb7", "woe:centroid": [153.416702, -29.1028], "geom:latitude": -29.1028, "geom:longitude": 153.416702, "geom:hash": "r6v47jfxukb7", "woe:latitude": -29.1028, "geom:centroid": [153.416702, -29.1028], "woe:longitude": 153.416702, "woe:repo": "woeplanet-airport-au", "geom:area": 0.0, "woe:scale": 19}}