{"type": "Feature", "id": 12510759, "properties": {"woe:id": 12510759, "woe:parent_id": 1100771, "woe:name": "Raaf Pearce Aerodrome", "woe:placetype": 14, "woe:placetype_name": "Airport", "woe:lang": "ENG", "iso:country": "AU", "meta:provider": ["geoplanet:7.3.1", "geoplanet:7.3.2", "geoplanet:7.4.0", "geoplanet:7.4.1", "geoplanet:7.5.1", "geoplanet:7.5.2", "geoplanet:7.6.0", "geoplanet:7.8.1", "geoplanet:7.9.0", "geoplanet:7.10.0", "geoplanet:8.0.0", "woeplanet:8.0.0"], "meta:indexed": "2020-08-20T20:56:50.338346", "woe:alias_ENG_V": ["Pearce Airport"], "meta:updated": "2020-08-22T02:29:09.597042", "woe:hierarchy": {"continent": 55949070, "country": 23424748, "town": 0, "planet": 1, "county": 55864409, "suburb": 0, "state": 2344706, "region": 0, "localadmin": 0}, "woe:timezone_id": 28350884, "woe:hash": "qd6eb62xvb5z", "woe:centroid": [116.02755, -31.670879], "geom:latitude": -31.670879, "geom:longitude": 116.02755, "geom:hash": "qd6eb62xvb5z", "woe:latitude": -31.670879, "geom:centroid": [116.02755, -31.670879], "woe:longitude": 116.02755, "woe:repo": "woeplanet-airport-au"}, "geometry": {"coordinates": [116.02755, -31.670879], "type": "Point"}}