{"type": "Feature", "id": 28677693, "properties": {"woe:id": 28677693, "woe:parent_id": 1103872, "woe:name": "Merty Merty Aerodrome", "woe:placetype": 14, "woe:placetype_name": "Airport", "woe:lang": "ENG", "iso:country": "AU", "meta:provider": ["geoplanet:7.3.1", "geoplanet:7.3.2", "geoplanet:7.4.0", "geoplanet:7.4.1", "geoplanet:7.5.1", "geoplanet:7.5.2", "geoplanet:7.6.0", "geoplanet:7.8.1", "geoplanet:7.9.0", "geoplanet:7.10.0", "geoplanet:8.0.0", "woeplanet:8.0.0"], "meta:indexed": "2020-08-20T20:56:50.172591", "meta:updated": "2020-08-22T02:29:09.520435", "woe:hierarchy": {"continent": 55949070, "country": 23424748, "town": 0, "planet": 1, "county": 0, "suburb": 0, "state": 2344703, "region": 0, "localadmin": 0}, "woe:timezone_id": 28350877, "woe:hash": "r4gv2syw32tf", "woe:centroid": [140.304398, -28.58123], "geom:latitude": -28.58123, "geom:longitude": 140.304398, "geom:hash": "r4gv2syw32tf", "woe:latitude": -28.58123, "geom:centroid": [140.304398, -28.58123], "woe:longitude": 140.304398, "woe:repo": "woeplanet-airport-au"}, "geometry": {"coordinates": [140.304398, -28.58123], "type": "Point"}}