{"type": "Feature", "id": 28677767, "properties": {"woe:id": 28677767, "woe:parent_id": 28585678, "woe:name": "Mount House Aerodrome", "woe:placetype": 14, "woe:placetype_name": "Airport", "woe:lang": "ENG", "iso:country": "AU", "meta:provider": ["geoplanet:7.3.1", "geoplanet:7.3.2", "geoplanet:7.4.0", "geoplanet:7.4.1", "geoplanet:7.5.1", "geoplanet:7.5.2", "geoplanet:7.6.0", "geoplanet:7.8.1", "geoplanet:7.9.0", "geoplanet:7.10.0", "geoplanet:8.0.0", "woeplanet:8.0.0"], "meta:indexed": "2020-08-20T20:56:50.228007", "woe:alias_ENG_V": ["Mt House Aerodrome"], "meta:updated": "2020-08-22T02:29:09.547027", "woe:hierarchy": {"continent": 55949070, "country": 23424748, "town": 0, "planet": 1, "county": 55864372, "suburb": 0, "state": 2344706, "region": 0, "localadmin": 0}, "woe:timezone_id": 28350884, "woe:hash": "qucqtc3wd9v1", "woe:centroid": [125.762672, -17.13068], "geom:latitude": -17.13068, "geom:longitude": 125.762672, "geom:hash": "qucqtc3wd9v1", "woe:latitude": -17.13068, "geom:centroid": [125.762672, -17.13068], "woe:longitude": 125.762672, "woe:repo": "woeplanet-airport-au"}, "geometry": {"coordinates": [125.762672, -17.13068], "type": "Point"}}