{"type": "Feature", "id": 12510682, "geometry": {"type": "Point", "coordinates": [136.462402, -13.97428]}, "properties": {"woe:id": 12510682, "woe:parent_id": 1099919, "woe:name": "Groote Eylandt Airport", "woe:placetype": 14, "woe:placetype_name": "Airport", "woe:lang": "ENG", "iso:country": "AU", "meta:provider": ["geoplanet:7.3.1", "geoplanet:7.3.2", "geoplanet:7.4.0", "geoplanet:7.4.1", "geoplanet:7.5.1", "geoplanet:7.5.2", "geoplanet:7.6.0", "geoplanet:7.8.1", "geoplanet:7.9.0", "geoplanet:7.10.0", "geoplanet:8.0.0", "woeplanet:8.0.0"], "meta:indexed": "2020-08-20T20:56:49.997498", "woe:alias_ENG_V": ["GTE Airport", "GTE"], "meta:updated": "2020-10-14T11:52:00.072666", "woe:hierarchy": {"continent": 55949070, "country": 23424748, "town": 0, "planet": 1, "county": 56072961, "suburb": 0, "state": 2344701, "region": 0, "localadmin": 0}, "woe:timezone_id": 28350879, "woe:hash": "rj90920cummu", "woe:centroid": [136.462402, -13.97428], "geom:latitude": -13.97428, "geom:longitude": 136.462402, "geom:hash": "rj90920cummu", "woe:latitude": -13.97428, "geom:centroid": [136.462402, -13.97428], "woe:longitude": 136.462402, "woe:repo": "woeplanet-airport-au", "geom:area": 0.0, "woe:scale": 19}}