{"type": "Feature", "id": 12510582, "properties": {"woe:id": 12510582, "woe:parent_id": 28584852, "woe:name": "Albany Airport", "woe:placetype": 14, "woe:placetype_name": "Airport", "woe:lang": "ENG", "iso:country": "AU", "meta:provider": ["geoplanet:7.3.1", "geoplanet:7.3.2", "geoplanet:7.4.0", "geoplanet:7.4.1", "geoplanet:7.5.1", "geoplanet:7.5.2", "geoplanet:7.6.0", "geoplanet:7.8.1", "geoplanet:7.9.0", "geoplanet:7.10.0", "geoplanet:8.0.0", "woeplanet:8.0.0"], "meta:indexed": "2020-08-20T20:56:50.277435", "woe:alias_ENG_V": ["ALH Airport", "ALH"], "meta:updated": "2020-08-22T02:29:09.567817", "woe:hierarchy": {"continent": 55949070, "country": 23424748, "town": 0, "planet": 1, "county": 55864168, "suburb": 0, "state": 2344706, "region": 0, "localadmin": 0}, "woe:timezone_id": 28350884, "woe:hash": "q9gc0wqh04nn", "woe:centroid": [117.803658, -34.945438], "geom:latitude": -34.945438, "geom:longitude": 117.803658, "geom:hash": "q9gc0wqh04nn", "woe:latitude": -34.945438, "geom:centroid": [117.803658, -34.945438], "woe:longitude": 117.803658, "woe:repo": "woeplanet-airport-au"}, "geometry": {"coordinates": [117.803658, -34.945438], "type": "Point"}}