{"type": "Feature", "id": 28677715, "properties": {"woe:id": 28677715, "woe:parent_id": 1094200, "woe:name": "Balfour Landing Ground", "woe:placetype": 14, "woe:placetype_name": "Airport", "woe:lang": "ENG", "iso:country": "AU", "meta:provider": ["geoplanet:7.3.1", "geoplanet:7.3.2", "geoplanet:7.4.0", "geoplanet:7.4.1", "geoplanet:7.5.1", "geoplanet:7.5.2", "geoplanet:7.6.0", "geoplanet:7.8.1", "geoplanet:7.9.0", "geoplanet:7.10.0", "geoplanet:8.0.0", "woeplanet:8.0.0"], "meta:indexed": "2020-08-20T20:56:50.188754", "meta:updated": "2020-08-22T02:29:09.528540", "woe:hierarchy": {"continent": 55949070, "country": 23424748, "town": 0, "planet": 1, "county": 55864272, "suburb": 0, "state": 2344704, "region": 0, "localadmin": 0}, "woe:timezone_id": 28350880, "woe:hash": "r0xj2byv1fng", "woe:centroid": [144.886063, -41.259659], "geom:latitude": -41.259659, "geom:longitude": 144.886063, "geom:hash": "r0xj2byv1fng", "woe:latitude": -41.259659, "geom:centroid": [144.886063, -41.259659], "woe:longitude": 144.886063, "woe:repo": "woeplanet-airport-au"}, "geometry": {"coordinates": [144.886063, -41.259659], "type": "Point"}}