{"type": "Feature", "id": 28677781, "geometry": {"type": "Point", "coordinates": [113.786667, -28.714861]}, "properties": {"woe:id": 28677781, "woe:parent_id": 28584951, "woe:name": "Rat Island Airport", "woe:placetype": 14, "woe:placetype_name": "Airport", "woe:lang": "ENG", "iso:country": "AU", "meta:provider": ["geoplanet:7.3.1", "geoplanet:7.3.2", "geoplanet:7.4.0", "geoplanet:7.4.1", "geoplanet:7.5.1", "geoplanet:7.5.2", "geoplanet:7.6.0", "geoplanet:7.8.1", "geoplanet:7.9.0", "geoplanet:7.10.0", "geoplanet:8.0.0", "woeplanet:8.0.0"], "meta:indexed": "2020-08-20T20:56:50.237872", "meta:updated": "2020-10-14T11:51:59.943647", "woe:hierarchy": {"continent": 55949070, "country": 23424748, "town": 0, "planet": 1, "county": 0, "suburb": 0, "state": 2344706, "region": 0, "localadmin": 0}, "woe:timezone_id": 28350884, "woe:hash": "qdbutk8gv9bq", "woe:centroid": [113.786667, -28.714861], "geom:latitude": -28.714861, "geom:longitude": 113.786667, "geom:hash": "qdbutk8gv9bq", "woe:latitude": -28.714861, "geom:centroid": [113.786667, -28.714861], "woe:longitude": 113.786667, "woe:repo": "woeplanet-airport-au", "geom:area": 0.0, "woe:scale": 19}}